<?xml version="1.0" encoding="UTF-8"?>
<flow id="b3f800b1-edf4-414f-8998-f0ac256b565a">
  <descriptionCdata><![CDATA[b3f800b1-edf4-414f-8998-f0ac256b565a.b24ce4aa-5ded-40fd-b02d-20dc05e583c6.description=<pre>\nThis workflow returns the details of the given service subscription id.\n\nInputs-\nsvcSubscriptionId \u2013   Service Subscription Id\nuserIdentifier  - User Identifier id\nauthType - The authentication type that this operation uses when trying to execute the request on the target server.\nValid values\: basic, form, digest, ntlm, kerberos, anonymous (no authentication).\nDefault value\: anonymous - authentication not used when executing the request.\nkerberosConfFile - The path to the Kerberos configuration file. If this input is empty the kdc (Key Distribution Center) and realm will get their values from the full domain name which is obtained from the url of the web server.\ntimeout - The number of milliseconds to wait for a connection to be established. This input should be assigned a value greater than or equal to zero. A timeout value of zero is an infinite timeout.\nDefault value\: 0.\nsocketTimeout - The number of milliseconds to wait for the data to be retrieved. This input should be assigned a value greater than or equal to zero. A socketTimeout value of zero is an infinite timeout.\nDefault value\: 0.\nuseCookies - If true, enables cookie tracking. Cookies will be stored between consecutive calls. This is a boolean input. If a non-boolean value is specified, it will take the default value.\nDefault value\: true.\nfollowRedirects - If true, the GET command automatically follows redirects. This is a boolean input. If a non-boolean value is specified, it will take the default value.\nDefault value\: true\nproxy - A proxy to use when accessing the web site.\nproxyPort - The port on the proxy to connect to.\nproxyUsername - The username to use when connecting to the proxy.\nproxyPassword - The password to use when connecting to the proxy.\nencodeURL - If true, automatically encodes the URL. This is a boolean input. If a non-boolean value is specified, it will take the default value.\nDefault value\: false.\nuserAgent - The value that should be used if the HTTP header USER_AGENT has to be overridden.\ntrustAllRoots - If true, enables weak security over SSL. A SSL certificate is trusted even if no trusted CA issued it.\nDefault value\: true\nkeystore - URL of the keystore file or local path to it (e.g. %JAVA_HOME%/jre/lib/security/cacerts). It may be empty if HTTPS client authentication is not to be used.\nkeystorePassword - Password to unlock the keystore.\ntrustKeystore - URL of the truststore file or local path to it (e.g. %JAVA_HOME%/jre/lib/security/cacerts). It may be empty if HTTPS server authentication is not to be used.\ntrustPassword - Password to unlock the truststore.\n\nOutputs-\nsubEndDate \u2013  Service subscription end date\nsubStartDate \u2013 Service subscription start date\ndocument  \u2013 returned XML document from API\n</pre>
]]></descriptionCdata>
  <annotation></annotation>
  <name>subs</name>
  <categories/>
  <inputs/>
  <possibleResponses>
    <opResponse id="0af9e902-b7ca-43e1-9b3d-586f370aa3d1">
      <annotation></annotation>
      <name>success</name>
      <isDefault>true</isDefault>
      <onFailure>false</onFailure>
      <type>RESOLVED</type>
      <matchRules/>
    </opResponse>
    <opResponse id="c44d46b5-1a90-49f4-a045-680b64ad72fe">
      <annotation></annotation>
      <name>failure</name>
      <isDefault>false</isDefault>
      <onFailure>true</onFailure>
      <type>ERROR</type>
      <matchRules/>
    </opResponse>
  </possibleResponses>
  <availableResultExpressions/>
  <resultExpression id="b664f11f-6918-403a-960a-4c2f7ee6ff2f">
    <annotation></annotation>
    <name>FailureMessage</name>
    <fieldName>FailureMessage</fieldName>
    <sourceType>RAWRESULT</sourceType>
    <filters/>
  </resultExpression>
  <iconSpec id="3c0f4858-e6b0-4fe6-88da-a540ff8a6635">
    <baseIcon>flow.png</baseIcon>
    <basePath>System</basePath>
    <readOnly>false</readOnly>
    <layers/>
  </iconSpec>
  <callouts/>
  <checkPointFlow>true</checkPointFlow>
  <compatibleRuntimeContext>false</compatibleRuntimeContext>
  <historyCheckPointFlow>true</historyCheckPointFlow>
  <steps>
    <step id="8b811559-84c5-4782-acf7-37c994a76548">
      <annotation></annotation>
      <name>Get User Identifier</name>
      <bounds>
        <x>248.0</x>
        <y>67.0</y>
      </bounds>
      <layer>-1</layer>
      <hideInbound>false</hideInbound>
      <addResultToRunContext>false</addResultToRunContext>
      <isCriticalStep>false</isCriticalStep>
      <isNonBlocking>false</isNonBlocking>
      <isParallelStep>false</isParallelStep>
      <isSingleResponse>false</isSingleResponse>
      <recordInHistory>false</recordInHistory>
      <recordRawOutput>false</recordRawOutput>
      <recordPrimaryOutput>false</recordPrimaryOutput>
      <checkPointStep>true</checkPointStep>
      <historyCheckPointStep>true</historyCheckPointStep>
      <scriptResultStep>false</scriptResultStep>
      <userPrompt></userPrompt>
      <bindings>
        <userInputBinding id="276b368d-1f35-4a31-8c65-91a75eda55e0">
          <annotation></annotation>
          <fromContextKey>CSA_OO_USER</fromContextKey>
          <assignFromContext>true</assignFromContext>
          <assignToContext>true</assignToContext>
          <inputType>STRING</inputType>
          <isList>false</isList>
          <required>true</required>
          <isPersisted>true</isPersisted>
          <inputSymbol>csaUser</inputSymbol>
          <listDelimiter>,</listDelimiter>
          <record>false</record>
          <prompt></prompt>
          <isMultiSelect>false</isMultiSelect>
          <sourceDelimiter>|</sourceDelimiter>
        </userInputBinding>
      </bindings>
      <transitions>
        <transition id="d1c5d017-9e42-4da9-ab87-c993b6019fa0">
          <annotation></annotation>
          <name>failure</name>
          <command>NEXT</command>
          <linkMode>false</linkMode>
          <responseSymbol>failure</responseSymbol>
          <shouldHandoff>false</shouldHandoff>
          <transitionValue>0.0</transitionValue>
          <destination>
            <refId>5a1ee81c-ecb9-4058-bb14-da23b2e58062</refId>
          </destination>
          <source>
            <refId>8b811559-84c5-4782-acf7-37c994a76548</refId>
          </source>
          <positions>
            <point>
              <x>298.0</x>
              <y>101.0</y>
            </point>
            <point>
              <x>353.0</x>
              <y>248.0</y>
            </point>
          </positions>
          <labelPosition>
            <x>333.0</x>
            <y>0.0</y>
          </labelPosition>
        </transition>
        <transition id="941181a5-d6d0-4ea3-a431-b9944de99acb">
          <annotation></annotation>
          <name>success</name>
          <command>NEXT</command>
          <linkMode>false</linkMode>
          <responseSymbol>success</responseSymbol>
          <shouldHandoff>false</shouldHandoff>
          <transitionValue>0.0</transitionValue>
          <destination>
            <refId>b24ce4aa-5ded-40fd-b02d-20dc05e583c6</refId>
          </destination>
          <source>
            <refId>8b811559-84c5-4782-acf7-37c994a76548</refId>
          </source>
          <positions>
            <point>
              <x>298.0</x>
              <y>101.0</y>
            </point>
            <point>
              <x>459.0</x>
              <y>116.0</y>
            </point>
          </positions>
          <labelPosition>
            <x>333.0</x>
            <y>0.0</y>
          </labelPosition>
        </transition>
      </transitions>
      <properties/>
      <opRef>
        <refId>f1c8b14a-694f-4a03-a84a-c7504fe0a29b</refId>
      </opRef>
      <assignments>
        <flowVariableAssignment id="916a8193-0c57-4bbf-ab58-6b5eda16660d">
          <annotation></annotation>
          <name>assignment</name>
          <action>OVERWRITE</action>
          <assignmentTargetType>FLOW_VARIABLE</assignmentTargetType>
          <contextKey>userIdentifier</contextKey>
          <expression id="af6302c3-c7eb-4fb2-86f3-ec30d0583981">
            <annotation></annotation>
            <name>Result Field: userIdentifier</name>
            <fieldName>userIdentifier</fieldName>
            <sourceType>RAWRESULT</sourceType>
            <filters/>
          </expression>
        </flowVariableAssignment>
      </assignments>
      <throttleSize>0</throttleSize>
    </step>
    <returnStep id="5a1ee81c-ecb9-4058-bb14-da23b2e58062">
      <annotation></annotation>
      <name>Error : failure</name>
      <bounds>
        <x>303.0</x>
        <y>214.0</y>
      </bounds>
      <layer>-1</layer>
      <hideInbound>false</hideInbound>
      <addResultToRunContext>false</addResultToRunContext>
      <isCriticalStep>false</isCriticalStep>
      <isNonBlocking>false</isNonBlocking>
      <isParallelStep>false</isParallelStep>
      <isSingleResponse>false</isSingleResponse>
      <recordInHistory>false</recordInHistory>
      <recordRawOutput>true</recordRawOutput>
      <recordPrimaryOutput>true</recordPrimaryOutput>
      <checkPointStep>true</checkPointStep>
      <historyCheckPointStep>true</historyCheckPointStep>
      <scriptResultStep>false</scriptResultStep>
      <userPrompt></userPrompt>
      <bindings/>
      <transitions>
        <transition id="1e1b7233-0b81-4f3a-ac77-4d12ea7b329e">
          <annotation></annotation>
          <name>return</name>
          <command>NEXT</command>
          <linkMode>false</linkMode>
          <responseSymbol>failure</responseSymbol>
          <shouldHandoff>false</shouldHandoff>
          <transitionValue>0.0</transitionValue>
          <destination>
            <refId>5a1ee81c-ecb9-4058-bb14-da23b2e58062</refId>
          </destination>
          <source>
            <refId>5a1ee81c-ecb9-4058-bb14-da23b2e58062</refId>
          </source>
          <positions/>
        </transition>
      </transitions>
      <properties/>
      <returnStepType>ERROR</returnStepType>
      <assignments/>
    </returnStep>
    <step id="b24ce4aa-5ded-40fd-b02d-20dc05e583c6">
      <annotation>b3f800b1-edf4-414f-8998-f0ac256b565a.b24ce4aa-5ded-40fd-b02d-20dc05e583c6.description</annotation>
      <name>Get Service Subscription Details</name>
      <bounds>
        <x>409.0</x>
        <y>67.0</y>
      </bounds>
      <layer>-1</layer>
      <hideInbound>false</hideInbound>
      <addResultToRunContext>false</addResultToRunContext>
      <isCriticalStep>false</isCriticalStep>
      <isNonBlocking>false</isNonBlocking>
      <isParallelStep>false</isParallelStep>
      <isSingleResponse>false</isSingleResponse>
      <recordInHistory>false</recordInHistory>
      <recordRawOutput>true</recordRawOutput>
      <recordPrimaryOutput>true</recordPrimaryOutput>
      <checkPointStep>true</checkPointStep>
      <historyCheckPointStep>true</historyCheckPointStep>
      <scriptResultStep>false</scriptResultStep>
      <userPrompt></userPrompt>
      <bindings>
        <staticBinding id="8bb4e6e1-d83c-48da-8d52-a46c95a7e13c">
          <annotation></annotation>
          <assignFromContext>false</assignFromContext>
          <assignToContext>false</assignToContext>
          <inputType>STRING</inputType>
          <isList>false</isList>
          <required>true</required>
          <isPersisted>true</isPersisted>
          <inputSymbol>svcSubscriptionId</inputSymbol>
          <listDelimiter>,</listDelimiter>
          <value>9038afc2567ed3310156923ce1da2aab</value>
          <record>false</record>
        </staticBinding>
        <userInputBinding id="6536db92-bb92-4279-b833-a0268f25cfa9">
          <annotation></annotation>
          <assignFromContext>true</assignFromContext>
          <assignToContext>false</assignToContext>
          <inputType>STRING</inputType>
          <isList>false</isList>
          <required>true</required>
          <isPersisted>true</isPersisted>
          <inputSymbol>userIdentifier</inputSymbol>
          <listDelimiter>,</listDelimiter>
          <record>false</record>
          <prompt></prompt>
          <isMultiSelect>false</isMultiSelect>
          <sourceDelimiter>|</sourceDelimiter>
        </userInputBinding>
        <staticBinding id="4d780e50-aa9b-46cc-aca7-825bc4342ff6">
          <annotation></annotation>
          <assignFromContext>false</assignFromContext>
          <assignToContext>false</assignToContext>
          <inputType>STRING</inputType>
          <isList>false</isList>
          <required>false</required>
          <isPersisted>true</isPersisted>
          <inputSymbol>timeout</inputSymbol>
          <listDelimiter>,</listDelimiter>
          <record>false</record>
        </staticBinding>
        <staticBinding id="79b1b8d1-7bb8-422c-adac-94dc9715a281">
          <annotation></annotation>
          <assignFromContext>false</assignFromContext>
          <assignToContext>false</assignToContext>
          <inputType>STRING</inputType>
          <isList>false</isList>
          <required>false</required>
          <isPersisted>true</isPersisted>
          <inputSymbol>socketTimeout</inputSymbol>
          <listDelimiter>,</listDelimiter>
          <record>false</record>
        </staticBinding>
        <staticBinding id="d563ec3b-26b6-4b96-b08e-9ad1538f1c80">
          <annotation></annotation>
          <assignFromContext>false</assignFromContext>
          <assignToContext>false</assignToContext>
          <inputType>STRING</inputType>
          <isList>false</isList>
          <required>false</required>
          <isPersisted>true</isPersisted>
          <inputSymbol>useCookies</inputSymbol>
          <listDelimiter>,</listDelimiter>
          <record>false</record>
        </staticBinding>
        <staticBinding id="b0bb6e48-c3d3-4e01-8b0f-b7f26dc84e9a">
          <annotation></annotation>
          <assignFromContext>false</assignFromContext>
          <assignToContext>false</assignToContext>
          <inputType>STRING</inputType>
          <isList>false</isList>
          <required>false</required>
          <isPersisted>true</isPersisted>
          <inputSymbol>trustAllRoots</inputSymbol>
          <listDelimiter>,</listDelimiter>
          <record>false</record>
        </staticBinding>
        <staticBinding id="dc941006-2786-49f8-a196-cd38c7481a27">
          <annotation></annotation>
          <assignFromContext>false</assignFromContext>
          <assignToContext>false</assignToContext>
          <inputType>STRING</inputType>
          <isList>false</isList>
          <required>false</required>
          <isPersisted>true</isPersisted>
          <inputSymbol>proxy</inputSymbol>
          <listDelimiter>,</listDelimiter>
          <record>false</record>
        </staticBinding>
        <staticBinding id="d7c12eb8-c837-4352-9e3f-ce74b161f045">
          <annotation></annotation>
          <assignFromContext>false</assignFromContext>
          <assignToContext>false</assignToContext>
          <inputType>STRING</inputType>
          <isList>false</isList>
          <required>false</required>
          <isPersisted>true</isPersisted>
          <inputSymbol>proxyPort</inputSymbol>
          <listDelimiter>,</listDelimiter>
          <record>false</record>
        </staticBinding>
        <staticBinding id="806946da-5b45-421a-a3ef-88eb20ae5e44">
          <annotation></annotation>
          <assignFromContext>false</assignFromContext>
          <assignToContext>false</assignToContext>
          <inputType>STRING</inputType>
          <isList>false</isList>
          <required>false</required>
          <isPersisted>true</isPersisted>
          <inputSymbol>proxyUsername</inputSymbol>
          <listDelimiter>,</listDelimiter>
          <record>false</record>
        </staticBinding>
        <staticBinding id="49c43600-50ee-4372-81b0-6777d3e46797">
          <annotation></annotation>
          <assignFromContext>false</assignFromContext>
          <assignToContext>false</assignToContext>
          <inputType>ENCRYPTED</inputType>
          <isList>false</isList>
          <required>false</required>
          <isPersisted>true</isPersisted>
          <inputSymbol>proxyPassword</inputSymbol>
          <listDelimiter>,</listDelimiter>
          <record>false</record>
        </staticBinding>
        <staticBinding id="5832d86b-5e51-479d-9e80-2ae0ee95c3c5">
          <annotation></annotation>
          <assignFromContext>false</assignFromContext>
          <assignToContext>false</assignToContext>
          <inputType>STRING</inputType>
          <isList>false</isList>
          <required>false</required>
          <isPersisted>true</isPersisted>
          <inputSymbol>encodeURL</inputSymbol>
          <listDelimiter>,</listDelimiter>
          <record>false</record>
        </staticBinding>
        <staticBinding id="7c26bb4a-eb0f-42fb-acd3-0ad85d3a8587">
          <annotation></annotation>
          <assignFromContext>false</assignFromContext>
          <assignToContext>false</assignToContext>
          <inputType>STRING</inputType>
          <isList>false</isList>
          <required>false</required>
          <isPersisted>true</isPersisted>
          <inputSymbol>followRedirects</inputSymbol>
          <listDelimiter>,</listDelimiter>
          <record>false</record>
        </staticBinding>
        <staticBinding id="0d9b7a95-2c74-4711-826c-0d8f91ca03c7">
          <annotation></annotation>
          <assignFromContext>false</assignFromContext>
          <assignToContext>false</assignToContext>
          <inputType>STRING</inputType>
          <isList>false</isList>
          <required>false</required>
          <isPersisted>true</isPersisted>
          <inputSymbol>userAgent</inputSymbol>
          <listDelimiter>,</listDelimiter>
          <record>false</record>
        </staticBinding>
        <staticBinding id="4f6eb79a-9d85-4819-8d33-66663a746993">
          <annotation></annotation>
          <assignFromContext>false</assignFromContext>
          <assignToContext>false</assignToContext>
          <inputType>STRING</inputType>
          <isList>false</isList>
          <required>false</required>
          <isPersisted>true</isPersisted>
          <inputSymbol>authType</inputSymbol>
          <listDelimiter>,</listDelimiter>
          <record>false</record>
        </staticBinding>
        <staticBinding id="9794a99e-6209-4290-90f6-36e7d7a67e29">
          <annotation></annotation>
          <assignFromContext>false</assignFromContext>
          <assignToContext>false</assignToContext>
          <inputType>STRING</inputType>
          <isList>false</isList>
          <required>false</required>
          <isPersisted>true</isPersisted>
          <inputSymbol>kerberosConfFile</inputSymbol>
          <listDelimiter>,</listDelimiter>
          <record>false</record>
        </staticBinding>
        <staticBinding id="a328d7ba-79fd-44a3-b4cf-307490763c97">
          <annotation></annotation>
          <assignFromContext>false</assignFromContext>
          <assignToContext>false</assignToContext>
          <inputType>STRING</inputType>
          <isList>false</isList>
          <required>false</required>
          <isPersisted>true</isPersisted>
          <inputSymbol>keystore</inputSymbol>
          <listDelimiter>,</listDelimiter>
          <record>false</record>
        </staticBinding>
        <staticBinding id="b05d20dc-50dd-4bf0-9ac1-7a6bb4f972f8">
          <annotation></annotation>
          <assignFromContext>false</assignFromContext>
          <assignToContext>false</assignToContext>
          <inputType>ENCRYPTED</inputType>
          <isList>false</isList>
          <required>false</required>
          <isPersisted>true</isPersisted>
          <inputSymbol>keystorePassword</inputSymbol>
          <listDelimiter>,</listDelimiter>
          <record>false</record>
        </staticBinding>
        <staticBinding id="2bd2d0ec-e456-4d9d-a46d-e8df82c8bbcd">
          <annotation></annotation>
          <assignFromContext>false</assignFromContext>
          <assignToContext>false</assignToContext>
          <inputType>STRING</inputType>
          <isList>false</isList>
          <required>false</required>
          <isPersisted>true</isPersisted>
          <inputSymbol>trustKeystore</inputSymbol>
          <listDelimiter>,</listDelimiter>
          <record>false</record>
        </staticBinding>
        <staticBinding id="41a9e6b1-06a7-41f3-bea7-73eb90b68334">
          <annotation></annotation>
          <assignFromContext>false</assignFromContext>
          <assignToContext>false</assignToContext>
          <inputType>ENCRYPTED</inputType>
          <isList>false</isList>
          <required>false</required>
          <isPersisted>true</isPersisted>
          <inputSymbol>trustPassword</inputSymbol>
          <listDelimiter>,</listDelimiter>
          <record>false</record>
        </staticBinding>
      </bindings>
      <transitions>
        <transition id="c6aea27b-c92d-4f39-a294-3ce5b3ab2b2a">
          <annotation></annotation>
          <name>success</name>
          <command>NEXT</command>
          <linkMode>false</linkMode>
          <responseSymbol>success</responseSymbol>
          <shouldHandoff>false</shouldHandoff>
          <transitionValue>0.0</transitionValue>
          <destination>
            <refId>b07cc58e-654e-476b-8e27-3d3d895a40b6</refId>
          </destination>
          <source>
            <refId>b24ce4aa-5ded-40fd-b02d-20dc05e583c6</refId>
          </source>
          <positions>
            <point>
              <x>459.0</x>
              <y>116.0</y>
            </point>
            <point>
              <x>615.0</x>
              <y>225.0</y>
            </point>
          </positions>
          <labelPosition>
            <x>333.0</x>
            <y>0.0</y>
          </labelPosition>
        </transition>
        <transition id="de57b8c5-f861-4475-990d-4338dd4fb57e">
          <annotation></annotation>
          <name>failure</name>
          <command>NEXT</command>
          <linkMode>false</linkMode>
          <responseSymbol>failure</responseSymbol>
          <shouldHandoff>false</shouldHandoff>
          <transitionValue>0.0</transitionValue>
          <destination>
            <refId>5a1ee81c-ecb9-4058-bb14-da23b2e58062</refId>
          </destination>
          <source>
            <refId>b24ce4aa-5ded-40fd-b02d-20dc05e583c6</refId>
          </source>
          <positions>
            <point>
              <x>459.0</x>
              <y>116.0</y>
            </point>
            <point>
              <x>353.0</x>
              <y>248.0</y>
            </point>
          </positions>
          <labelPosition>
            <x>333.0</x>
            <y>0.0</y>
          </labelPosition>
        </transition>
      </transitions>
      <properties/>
      <opRef>
        <refId>787cac2a-bca3-4da9-b0dc-562c0359eb98</refId>
      </opRef>
      <assignments/>
      <throttleSize>0</throttleSize>
    </step>
    <returnStep id="b07cc58e-654e-476b-8e27-3d3d895a40b6">
      <annotation></annotation>
      <name>Resolved : success</name>
      <bounds>
        <x>583.0</x>
        <y>67.0</y>
      </bounds>
      <layer>-1</layer>
      <hideInbound>false</hideInbound>
      <addResultToRunContext>false</addResultToRunContext>
      <isCriticalStep>false</isCriticalStep>
      <isNonBlocking>false</isNonBlocking>
      <isParallelStep>false</isParallelStep>
      <isSingleResponse>false</isSingleResponse>
      <recordInHistory>false</recordInHistory>
      <recordRawOutput>true</recordRawOutput>
      <recordPrimaryOutput>true</recordPrimaryOutput>
      <checkPointStep>true</checkPointStep>
      <historyCheckPointStep>true</historyCheckPointStep>
      <scriptResultStep>false</scriptResultStep>
      <userPrompt></userPrompt>
      <bindings/>
      <transitions>
        <transition id="8ed8fe11-a52d-4d4f-934c-84cb81556b8e">
          <annotation></annotation>
          <name>return</name>
          <command>NEXT</command>
          <linkMode>false</linkMode>
          <responseSymbol>success</responseSymbol>
          <shouldHandoff>false</shouldHandoff>
          <transitionValue>0.0</transitionValue>
          <destination>
            <refId>b07cc58e-654e-476b-8e27-3d3d895a40b6</refId>
          </destination>
          <source>
            <refId>b07cc58e-654e-476b-8e27-3d3d895a40b6</refId>
          </source>
          <positions/>
        </transition>
      </transitions>
      <properties/>
      <returnStepType>RESOLVED</returnStepType>
      <assignments/>
    </returnStep>
  </steps>
  <startSteps>8b811559-84c5-4782-acf7-37c994a76548</startSteps>
</flow>