<?xml version="1.0" encoding="UTF-8"?>
<flow id="32fb6761-dd35-44f8-a349-6c391d2650b4">
  <descriptionCdata><![CDATA[32fb6761-dd35-44f8-a349-6c391d2650b4.0633dafc-b74b-40ec-aae8-f13969965b24.description=This workflow returns the artifact's properties and values using Artifact APIs.\n\nresult\:\npropertyNameValuesList\: pipe separated list of property name and values ( where each property name and values would be ; seprated and multiple values would be , seprated)\ne.g. - property 1; value1,value2|property 2; value3|property 3; value3,value4|........
32fb6761-dd35-44f8-a349-6c391d2650b4.0e0585fe-309d-4da3-a928-85e17a4d1758.prompt=Enter a value for value1
32fb6761-dd35-44f8-a349-6c391d2650b4.1082a937-e0c0-4cbd-b756-f7d0dcd489ed.prompt=Artifact ID
32fb6761-dd35-44f8-a349-6c391d2650b4.22ac4175-4316-4f1f-8bc5-58563c1c2e13.prompt=Service Component Id
32fb6761-dd35-44f8-a349-6c391d2650b4.2a5e67a0-ea9e-498b-b4e7-651a67509cdb.prompt=User Identifier
32fb6761-dd35-44f8-a349-6c391d2650b4.2bea90ee-08a2-4090-9fa5-5ef5af95b4d9.description=<pre>\nAdds two numbers together\n\nInputs\:\nvalue1 - The first value.\nvalue2 - The second value.\n\nReturns\:\nThe sum of the two numbers.\n\nResponses\:\nsuccess - The operation completed successfully.\nfailure - Something went wrong.\n</pre>
32fb6761-dd35-44f8-a349-6c391d2650b4.3a009096-ad7f-4830-a3ed-d732490b51e3.prompt=Service Instance Id
32fb6761-dd35-44f8-a349-6c391d2650b4.48bff1a8-5fff-423b-8be7-931ba2accde5.prompt=Component ID
32fb6761-dd35-44f8-a349-6c391d2650b4.58caf5a2-011e-4ff8-9af8-e5587d74456e.description=This workflow adds/updates the component property using Artifact APIs.\n\nonlyUpdate\: yes/no \nyes - To update values of existing property (In this case input "valueType" is not required , This input will not be considered even if provided)\nno - To add/update property\n\nvalueType - Value type of the property. It can have value from selection list "CSA-Property-ValueType". This Input is required only when Input "onlyUpdate" is selected as "no".\nvalues - One or more values dilimited by comma , (If user want to use some other separator for multiple values then needs to be pass as next input "separator")\nseparator -  A delimiter that separates elements in the values ( default dilimiter used is comma ,)
32fb6761-dd35-44f8-a349-6c391d2650b4.7a81fa68-e3fe-4456-83b0-41122c13bc61.prompt=Service Component Id
32fb6761-dd35-44f8-a349-6c391d2650b4.9e9f0aeb-7a4e-458e-a280-ac8e9e428d7d.prompt=User Identifier
32fb6761-dd35-44f8-a349-6c391d2650b4.description=<pre>\nAdd Server Components to Server Group and Provision a clone server \n\nInput Parameters\:\nserverGrpId - Server Group Component Id\nserviceInstanceId - Service Instance Id of the Subscription\naddServers - Number of Servers to be added\nuserIdentifier - OO Application UUID to authorize a REST Call\n\nResponses\:\n   success -  if the command completes execution and its exit code is 0\n   failure - otherwise\n\nResult Fields\:\n NA\n</pre>
]]></descriptionCdata>
  <annotation>32fb6761-dd35-44f8-a349-6c391d2650b4.description</annotation>
  <name>CloneChildTrigger</name>
  <categories/>
  <inputs>
    <userInputBinding id="e4709a07-030b-4695-9418-52276c2ffe2b">
      <annotation></annotation>
      <assignFromContext>true</assignFromContext>
      <assignToContext>true</assignToContext>
      <inputType>STRING</inputType>
      <isList>false</isList>
      <required>true</required>
      <isPersisted>true</isPersisted>
      <inputSymbol>serverGrpId</inputSymbol>
      <listDelimiter>,</listDelimiter>
      <record>false</record>
      <prompt></prompt>
      <isMultiSelect>false</isMultiSelect>
      <sourceDelimiter>|</sourceDelimiter>
    </userInputBinding>
    <userInputBinding id="1c2e8c72-8297-4a9d-ac1c-bf30203dd34d">
      <annotation></annotation>
      <assignFromContext>true</assignFromContext>
      <assignToContext>true</assignToContext>
      <inputType>STRING</inputType>
      <isList>false</isList>
      <required>true</required>
      <isPersisted>true</isPersisted>
      <inputSymbol>serviceInstanceId</inputSymbol>
      <listDelimiter>,</listDelimiter>
      <record>false</record>
      <prompt></prompt>
      <isMultiSelect>false</isMultiSelect>
      <sourceDelimiter>|</sourceDelimiter>
    </userInputBinding>
    <userInputBinding id="4f1c7c3a-2dc5-4f6f-9ced-df189d60b6cc">
      <annotation></annotation>
      <assignFromContext>true</assignFromContext>
      <assignToContext>true</assignToContext>
      <inputType>STRING</inputType>
      <isList>false</isList>
      <required>true</required>
      <isPersisted>true</isPersisted>
      <inputSymbol>userIdentifier</inputSymbol>
      <listDelimiter>,</listDelimiter>
      <record>false</record>
      <prompt></prompt>
      <isMultiSelect>false</isMultiSelect>
      <sourceDelimiter>|</sourceDelimiter>
    </userInputBinding>
    <userInputBinding id="4108d6f6-6c4b-4804-bd4b-bec6ed8bd533">
      <annotation></annotation>
      <assignFromContext>true</assignFromContext>
      <assignToContext>true</assignToContext>
      <inputType>STRING</inputType>
      <isList>false</isList>
      <required>true</required>
      <isPersisted>true</isPersisted>
      <inputSymbol>addServers</inputSymbol>
      <listDelimiter>,</listDelimiter>
      <record>false</record>
      <prompt></prompt>
      <isMultiSelect>false</isMultiSelect>
      <sourceDelimiter>|</sourceDelimiter>
    </userInputBinding>
  </inputs>
  <possibleResponses>
    <opResponse id="44fc77cb-6ba8-4fbe-a042-31dd10425bce">
      <annotation></annotation>
      <name>success</name>
      <isDefault>true</isDefault>
      <onFailure>false</onFailure>
      <type>RESOLVED</type>
      <matchRules/>
    </opResponse>
    <opResponse id="62b25438-9b46-4593-8f4a-07db27f5bec1">
      <annotation></annotation>
      <name>failure</name>
      <isDefault>false</isDefault>
      <onFailure>true</onFailure>
      <type>ERROR</type>
      <matchRules/>
    </opResponse>
  </possibleResponses>
  <availableResultExpressions/>
  <resultExpression id="abdf3217-e6d4-475a-b403-99826c9a32a2">
    <annotation></annotation>
    <name>FailureMessage</name>
    <fieldName>FailureMessage</fieldName>
    <sourceType>RAWRESULT</sourceType>
    <filters/>
  </resultExpression>
  <iconSpec id="265c691e-8583-40e4-bce2-56dcb037e175">
    <baseIcon>flow.png</baseIcon>
    <basePath>System</basePath>
    <readOnly>false</readOnly>
    <layers/>
  </iconSpec>
  <callouts/>
  <checkPointFlow>true</checkPointFlow>
  <compatibleRuntimeContext>false</compatibleRuntimeContext>
  <historyCheckPointFlow>true</historyCheckPointFlow>
  <steps>
    <step id="0633dafc-b74b-40ec-aae8-f13969965b24">
      <annotation>32fb6761-dd35-44f8-a349-6c391d2650b4.0633dafc-b74b-40ec-aae8-f13969965b24.description</annotation>
      <name>Get Pattern</name>
      <bounds>
        <x>155.0</x>
        <y>119.0</y>
      </bounds>
      <layer>-1</layer>
      <hideInbound>false</hideInbound>
      <iconSpec id="697c602f-b1f3-4890-bcd8-9f28c2f9be7e">
        <baseIcon>flow.png</baseIcon>
        <basePath>System</basePath>
        <readOnly>false</readOnly>
        <layers/>
      </iconSpec>
      <addResultToRunContext>false</addResultToRunContext>
      <isCriticalStep>false</isCriticalStep>
      <isNonBlocking>false</isNonBlocking>
      <isParallelStep>false</isParallelStep>
      <isSingleResponse>false</isSingleResponse>
      <recordInHistory>false</recordInHistory>
      <recordRawOutput>false</recordRawOutput>
      <recordPrimaryOutput>false</recordPrimaryOutput>
      <checkPointStep>true</checkPointStep>
      <historyCheckPointStep>true</historyCheckPointStep>
      <scriptResultStep>false</scriptResultStep>
      <userPrompt></userPrompt>
      <bindings>
        <userInputBinding id="1082a937-e0c0-4cbd-b756-f7d0dcd489ed">
          <annotation></annotation>
          <fromContextKey>serverGrpId</fromContextKey>
          <assignFromContext>true</assignFromContext>
          <assignToContext>true</assignToContext>
          <inputType>STRING</inputType>
          <isList>false</isList>
          <required>true</required>
          <isPersisted>true</isPersisted>
          <inputSymbol>artifactId</inputSymbol>
          <listDelimiter>,</listDelimiter>
          <record>false</record>
          <prompt>32fb6761-dd35-44f8-a349-6c391d2650b4.1082a937-e0c0-4cbd-b756-f7d0dcd489ed.prompt</prompt>
          <isMultiSelect>false</isMultiSelect>
          <sourceDelimiter>|</sourceDelimiter>
        </userInputBinding>
        <userInputBinding id="9e9f0aeb-7a4e-458e-a280-ac8e9e428d7d">
          <annotation></annotation>
          <assignFromContext>true</assignFromContext>
          <assignToContext>true</assignToContext>
          <inputType>STRING</inputType>
          <isList>false</isList>
          <required>true</required>
          <isPersisted>true</isPersisted>
          <inputSymbol>userIdentifier</inputSymbol>
          <listDelimiter>,</listDelimiter>
          <record>false</record>
          <prompt>32fb6761-dd35-44f8-a349-6c391d2650b4.9e9f0aeb-7a4e-458e-a280-ac8e9e428d7d.prompt</prompt>
          <isMultiSelect>false</isMultiSelect>
          <sourceDelimiter>|</sourceDelimiter>
        </userInputBinding>
        <staticBinding id="27657376-d1c5-4c42-b3f2-9bf9abf8b962">
          <annotation></annotation>
          <assignFromContext>true</assignFromContext>
          <assignToContext>true</assignToContext>
          <inputType>STRING</inputType>
          <isList>false</isList>
          <required>false</required>
          <isPersisted>true</isPersisted>
          <inputSymbol>propertyNames</inputSymbol>
          <listDelimiter>,</listDelimiter>
          <value>count</value>
          <record>false</record>
        </staticBinding>
      </bindings>
      <transitions>
        <transition id="82bbfd86-a8d3-44e1-895b-a4a8326e94d4">
          <annotation></annotation>
          <name>success</name>
          <command>NEXT</command>
          <linkMode>false</linkMode>
          <responseSymbol>success</responseSymbol>
          <shouldHandoff>false</shouldHandoff>
          <transitionValue>0.0</transitionValue>
          <destination>
            <refId>2bea90ee-08a2-4090-9fa5-5ef5af95b4d9</refId>
          </destination>
          <source>
            <refId>0633dafc-b74b-40ec-aae8-f13969965b24</refId>
          </source>
          <positions>
            <point>
              <x>205.0</x>
              <y>153.0</y>
            </point>
            <point>
              <x>293.0</x>
              <y>25.0</y>
            </point>
          </positions>
          <labelPosition>
            <x>333.0</x>
            <y>0.0</y>
          </labelPosition>
        </transition>
        <transition id="8a516bda-d57a-4c5f-b113-790c9159eac8">
          <annotation></annotation>
          <name>failure</name>
          <command>NEXT</command>
          <linkMode>false</linkMode>
          <responseSymbol>failure</responseSymbol>
          <shouldHandoff>false</shouldHandoff>
          <transitionValue>0.0</transitionValue>
          <destination>
            <refId>65281656-4a99-4ace-a063-20addf7b4090</refId>
          </destination>
          <source>
            <refId>0633dafc-b74b-40ec-aae8-f13969965b24</refId>
          </source>
          <positions>
            <point>
              <x>205.0</x>
              <y>153.0</y>
            </point>
            <point>
              <x>379.0</x>
              <y>259.0</y>
            </point>
          </positions>
          <labelPosition>
            <x>333.0</x>
            <y>0.0</y>
          </labelPosition>
        </transition>
      </transitions>
      <properties/>
      <opRef>
        <refId>299ef3d3-42ca-4c36-8c0e-46ade1e339f5</refId>
      </opRef>
      <assignments>
        <flowVariableAssignment id="e4c776ac-7015-4199-a81a-800965fab7e5">
          <annotation></annotation>
          <name>assignment</name>
          <action>OVERWRITE</action>
          <assignmentTargetType>FLOW_VARIABLE</assignmentTargetType>
          <contextKey>patternCount</contextKey>
          <expression id="15c2249e-15c4-4f26-b571-f7cc932fedd1">
            <annotation></annotation>
            <name>Result Field: propertyNameValuesList</name>
            <fieldName>propertyNameValuesList</fieldName>
            <sourceType>RAWRESULT</sourceType>
            <filters>
              <stripTrailingFilter id="7209f1a3-cbc5-4fe8-8566-f2317b174d56">
                <annotation></annotation>
                <name>Strip</name>
                <strip>count;</strip>
                <type>ALL_CHARACTERS_UP_TO_AND_INCLUDING</type>
              </stripTrailingFilter>
              <stripTrailingFilter id="6ce26697-afcd-40f2-94a0-0b73423d996c">
                <annotation></annotation>
                <name>Strip</name>
                <strip>|</strip>
                <type>ALL_CHARACTERS_AFTER_AND_INCLUDING</type>
              </stripTrailingFilter>
            </filters>
          </expression>
        </flowVariableAssignment>
      </assignments>
      <throttleSize>0</throttleSize>
    </step>
    <step id="33515130-d3a5-4d79-b8b9-f4f320029371">
      <annotation></annotation>
      <name>ExecuteProcess Instance</name>
      <bounds>
        <x>702.0</x>
        <y>19.0</y>
      </bounds>
      <layer>-1</layer>
      <hideInbound>false</hideInbound>
      <addResultToRunContext>false</addResultToRunContext>
      <isCriticalStep>false</isCriticalStep>
      <isNonBlocking>false</isNonBlocking>
      <isParallelStep>false</isParallelStep>
      <isSingleResponse>false</isSingleResponse>
      <recordInHistory>false</recordInHistory>
      <recordRawOutput>false</recordRawOutput>
      <recordPrimaryOutput>false</recordPrimaryOutput>
      <checkPointStep>true</checkPointStep>
      <historyCheckPointStep>true</historyCheckPointStep>
      <scriptResultStep>false</scriptResultStep>
      <userPrompt></userPrompt>
      <bindings>
        <userInputBinding id="43adcbce-cd61-43ed-a2bc-69e3aeec3b7e">
          <annotation></annotation>
          <assignFromContext>true</assignFromContext>
          <assignToContext>true</assignToContext>
          <inputType>STRING</inputType>
          <isList>false</isList>
          <required>true</required>
          <isPersisted>true</isPersisted>
          <inputSymbol>userIdentifier</inputSymbol>
          <listDelimiter>,</listDelimiter>
          <record>false</record>
          <prompt></prompt>
          <isMultiSelect>false</isMultiSelect>
          <sourceDelimiter>|</sourceDelimiter>
        </userInputBinding>
        <userInputBinding id="74ac06f8-3be8-4f85-84e1-48c0f3d28096">
          <annotation></annotation>
          <assignFromContext>true</assignFromContext>
          <assignToContext>true</assignToContext>
          <inputType>STRING</inputType>
          <isList>false</isList>
          <required>true</required>
          <isPersisted>true</isPersisted>
          <inputSymbol>processInstanceId</inputSymbol>
          <listDelimiter>,</listDelimiter>
          <record>false</record>
          <prompt></prompt>
          <isMultiSelect>false</isMultiSelect>
          <sourceDelimiter>|</sourceDelimiter>
        </userInputBinding>
      </bindings>
      <transitions>
        <transition id="c250a03d-82e4-4fee-84f1-455fed7ca403">
          <annotation></annotation>
          <name>failure</name>
          <command>NEXT</command>
          <linkMode>false</linkMode>
          <responseSymbol>failure</responseSymbol>
          <shouldHandoff>false</shouldHandoff>
          <transitionValue>0.0</transitionValue>
          <destination>
            <refId>65281656-4a99-4ace-a063-20addf7b4090</refId>
          </destination>
          <source>
            <refId>33515130-d3a5-4d79-b8b9-f4f320029371</refId>
          </source>
          <positions>
            <point>
              <x>848.0</x>
              <y>122.0</y>
            </point>
            <point>
              <x>650.0</x>
              <y>255.0</y>
            </point>
          </positions>
          <labelPosition>
            <x>333.0</x>
            <y>0.0</y>
          </labelPosition>
        </transition>
        <transition id="4758d6bb-735a-4707-ab8a-d19386d4d564">
          <annotation></annotation>
          <name>success</name>
          <command>NEXT</command>
          <linkMode>false</linkMode>
          <responseSymbol>success</responseSymbol>
          <shouldHandoff>false</shouldHandoff>
          <transitionValue>0.0</transitionValue>
          <destination>
            <refId>8cf69600-4e13-460e-95cf-c34bf76535eb</refId>
          </destination>
          <source>
            <refId>33515130-d3a5-4d79-b8b9-f4f320029371</refId>
          </source>
          <positions>
            <point>
              <x>624.0</x>
              <y>79.0</y>
            </point>
            <point>
              <x>809.0</x>
              <y>262.0</y>
            </point>
          </positions>
          <labelPosition>
            <x>333.0</x>
            <y>0.0</y>
          </labelPosition>
        </transition>
      </transitions>
      <properties/>
      <opRef>
        <refId>fc818c6d-7b24-40de-a6a4-f5bdacdb3967</refId>
      </opRef>
      <assignments/>
      <throttleSize>0</throttleSize>
    </step>
    <step id="58caf5a2-011e-4ff8-9af8-e5587d74456e">
      <annotation>32fb6761-dd35-44f8-a349-6c391d2650b4.58caf5a2-011e-4ff8-9af8-e5587d74456e.description</annotation>
      <name>Update Pattern</name>
      <bounds>
        <x>387.0</x>
        <y>0.0</y>
      </bounds>
      <layer>-1</layer>
      <hideInbound>false</hideInbound>
      <addResultToRunContext>false</addResultToRunContext>
      <isCriticalStep>false</isCriticalStep>
      <isNonBlocking>false</isNonBlocking>
      <isParallelStep>false</isParallelStep>
      <isSingleResponse>false</isSingleResponse>
      <recordInHistory>false</recordInHistory>
      <recordRawOutput>false</recordRawOutput>
      <recordPrimaryOutput>false</recordPrimaryOutput>
      <checkPointStep>true</checkPointStep>
      <historyCheckPointStep>true</historyCheckPointStep>
      <scriptResultStep>false</scriptResultStep>
      <userPrompt></userPrompt>
      <bindings>
        <userInputBinding id="48bff1a8-5fff-423b-8be7-931ba2accde5">
          <annotation></annotation>
          <fromContextKey>serverGrpId</fromContextKey>
          <assignFromContext>true</assignFromContext>
          <assignToContext>true</assignToContext>
          <inputType>STRING</inputType>
          <isList>false</isList>
          <required>true</required>
          <isPersisted>true</isPersisted>
          <inputSymbol>componentId</inputSymbol>
          <listDelimiter>,</listDelimiter>
          <record>false</record>
          <prompt>32fb6761-dd35-44f8-a349-6c391d2650b4.48bff1a8-5fff-423b-8be7-931ba2accde5.prompt</prompt>
          <isMultiSelect>false</isMultiSelect>
          <sourceDelimiter>|</sourceDelimiter>
        </userInputBinding>
        <userInputBinding id="2a5e67a0-ea9e-498b-b4e7-651a67509cdb">
          <annotation></annotation>
          <assignFromContext>true</assignFromContext>
          <assignToContext>true</assignToContext>
          <inputType>STRING</inputType>
          <isList>false</isList>
          <required>true</required>
          <isPersisted>true</isPersisted>
          <inputSymbol>userIdentifier</inputSymbol>
          <listDelimiter>,</listDelimiter>
          <record>false</record>
          <prompt>32fb6761-dd35-44f8-a349-6c391d2650b4.2a5e67a0-ea9e-498b-b4e7-651a67509cdb.prompt</prompt>
          <isMultiSelect>false</isMultiSelect>
          <sourceDelimiter>|</sourceDelimiter>
        </userInputBinding>
        <staticBinding id="23d487c9-e2dd-48b5-9be0-d07a8427ddaa">
          <annotation></annotation>
          <assignFromContext>true</assignFromContext>
          <assignToContext>true</assignToContext>
          <inputType>STRING</inputType>
          <isList>false</isList>
          <required>false</required>
          <isPersisted>true</isPersisted>
          <inputSymbol>onlyUpdate</inputSymbol>
          <listDelimiter>,</listDelimiter>
          <value>yes</value>
          <record>false</record>
        </staticBinding>
        <staticBinding id="fd067dea-d665-4f77-98a7-1c859edc2176">
          <annotation></annotation>
          <assignFromContext>false</assignFromContext>
          <assignToContext>false</assignToContext>
          <inputType>STRING</inputType>
          <isList>false</isList>
          <required>false</required>
          <isPersisted>true</isPersisted>
          <inputSymbol>displayName</inputSymbol>
          <listDelimiter>,</listDelimiter>
          <value>count</value>
          <record>false</record>
        </staticBinding>
        <staticBinding id="b5412702-20c7-4790-9cf1-1bf34deca0d4">
          <annotation></annotation>
          <assignFromContext>false</assignFromContext>
          <assignToContext>true</assignToContext>
          <inputType>STRING</inputType>
          <isList>false</isList>
          <required>false</required>
          <isPersisted>true</isPersisted>
          <inputSymbol>propertyName</inputSymbol>
          <listDelimiter>,</listDelimiter>
          <value>count</value>
          <record>false</record>
        </staticBinding>
        <staticBinding id="15c96fbb-45b7-4581-8b0a-f923720cf21b">
          <annotation></annotation>
          <assignFromContext>true</assignFromContext>
          <assignToContext>true</assignToContext>
          <inputType>STRING</inputType>
          <isList>false</isList>
          <required>false</required>
          <isPersisted>true</isPersisted>
          <inputSymbol>valueType</inputSymbol>
          <listDelimiter>,</listDelimiter>
          <value></value>
          <record>false</record>
        </staticBinding>
        <staticBinding id="865e5a15-35b3-461b-832b-443417d41274">
          <annotation></annotation>
          <fromContextKey>SVC_COMPONENT_ID</fromContextKey>
          <assignFromContext>false</assignFromContext>
          <assignToContext>true</assignToContext>
          <inputType>STRING</inputType>
          <isList>false</isList>
          <required>false</required>
          <isPersisted>true</isPersisted>
          <inputSymbol>values</inputSymbol>
          <listDelimiter>,</listDelimiter>
          <value>${patternCount}</value>
          <record>false</record>
        </staticBinding>
        <staticBinding id="514b7a58-9fa7-44c1-ab35-24ddf8e5fb5c">
          <annotation></annotation>
          <assignFromContext>true</assignFromContext>
          <assignToContext>true</assignToContext>
          <inputType>STRING</inputType>
          <isList>false</isList>
          <required>false</required>
          <isPersisted>true</isPersisted>
          <inputSymbol>separator</inputSymbol>
          <listDelimiter>,</listDelimiter>
          <value>,</value>
          <record>false</record>
        </staticBinding>
      </bindings>
      <transitions>
        <transition id="0a07cd28-2457-42bf-af7c-bd95c76689ff">
          <annotation></annotation>
          <name>failure</name>
          <command>NEXT</command>
          <linkMode>false</linkMode>
          <responseSymbol>failure</responseSymbol>
          <shouldHandoff>false</shouldHandoff>
          <transitionValue>0.0</transitionValue>
          <destination>
            <refId>65281656-4a99-4ace-a063-20addf7b4090</refId>
          </destination>
          <source>
            <refId>58caf5a2-011e-4ff8-9af8-e5587d74456e</refId>
          </source>
          <positions>
            <point>
              <x>518.0</x>
              <y>68.0</y>
            </point>
            <point>
              <x>650.0</x>
              <y>255.0</y>
            </point>
          </positions>
          <labelPosition>
            <x>333.0</x>
            <y>0.0</y>
          </labelPosition>
        </transition>
        <transition id="8dedfb4a-5da6-4f47-a535-7c7bdaf72fdb">
          <annotation></annotation>
          <name>success</name>
          <command>NEXT</command>
          <linkMode>false</linkMode>
          <responseSymbol>success</responseSymbol>
          <shouldHandoff>false</shouldHandoff>
          <transitionValue>0.0</transitionValue>
          <destination>
            <refId>85eeedc0-a8c8-4179-898c-46f6613ac26c</refId>
          </destination>
          <source>
            <refId>58caf5a2-011e-4ff8-9af8-e5587d74456e</refId>
          </source>
          <positions>
            <point>
              <x>293.0</x>
              <y>75.0</y>
            </point>
            <point>
              <x>424.0</x>
              <y>73.0</y>
            </point>
          </positions>
          <labelPosition>
            <x>333.0</x>
            <y>0.0</y>
          </labelPosition>
        </transition>
      </transitions>
      <properties/>
      <opRef>
        <refId>fe69637d-9835-4aea-912f-844b4bc189bf</refId>
      </opRef>
      <assignments/>
      <throttleSize>0</throttleSize>
    </step>
    <step id="8cf69600-4e13-460e-95cf-c34bf76535eb">
      <annotation></annotation>
      <name>Poll Process Instance</name>
      <bounds>
        <x>745.0</x>
        <y>179.0</y>
      </bounds>
      <layer>-1</layer>
      <hideInbound>false</hideInbound>
      <addResultToRunContext>false</addResultToRunContext>
      <isCriticalStep>false</isCriticalStep>
      <isNonBlocking>false</isNonBlocking>
      <isParallelStep>false</isParallelStep>
      <isSingleResponse>false</isSingleResponse>
      <recordInHistory>false</recordInHistory>
      <recordRawOutput>false</recordRawOutput>
      <recordPrimaryOutput>false</recordPrimaryOutput>
      <checkPointStep>true</checkPointStep>
      <historyCheckPointStep>true</historyCheckPointStep>
      <scriptResultStep>false</scriptResultStep>
      <userPrompt></userPrompt>
      <bindings>
        <userInputBinding id="b60f17e5-5580-4e62-b820-8f3e82850839">
          <annotation></annotation>
          <assignFromContext>true</assignFromContext>
          <assignToContext>true</assignToContext>
          <inputType>STRING</inputType>
          <isList>false</isList>
          <required>false</required>
          <isPersisted>true</isPersisted>
          <inputSymbol>userIdentifier</inputSymbol>
          <listDelimiter>,</listDelimiter>
          <record>false</record>
          <prompt></prompt>
          <isMultiSelect>false</isMultiSelect>
          <sourceDelimiter>|</sourceDelimiter>
        </userInputBinding>
        <userInputBinding id="3ce97a53-9b96-4416-919c-ac859e4aedfb">
          <annotation></annotation>
          <assignFromContext>true</assignFromContext>
          <assignToContext>true</assignToContext>
          <inputType>STRING</inputType>
          <isList>false</isList>
          <required>true</required>
          <isPersisted>true</isPersisted>
          <inputSymbol>processInstanceId</inputSymbol>
          <listDelimiter>,</listDelimiter>
          <record>false</record>
          <prompt></prompt>
          <isMultiSelect>false</isMultiSelect>
          <sourceDelimiter>|</sourceDelimiter>
        </userInputBinding>
      </bindings>
      <transitions>
        <transition id="060cf977-9ef0-4860-b669-12330386ccad">
          <annotation></annotation>
          <name>success</name>
          <command>NEXT</command>
          <linkMode>false</linkMode>
          <responseSymbol>success</responseSymbol>
          <shouldHandoff>false</shouldHandoff>
          <transitionValue>0.0</transitionValue>
          <destination>
            <refId>2b32adc4-486d-49c0-a56f-507bccff5c68</refId>
          </destination>
          <source>
            <refId>8cf69600-4e13-460e-95cf-c34bf76535eb</refId>
          </source>
          <positions>
            <point>
              <x>809.0</x>
              <y>262.0</y>
            </point>
            <point>
              <x>694.0</x>
              <y>330.0</y>
            </point>
          </positions>
          <labelPosition>
            <x>333.0</x>
            <y>0.0</y>
          </labelPosition>
        </transition>
        <transition id="2f6ae035-2bb0-40b5-a946-01a476c2eda7">
          <annotation></annotation>
          <name>failure</name>
          <command>NEXT</command>
          <linkMode>false</linkMode>
          <responseSymbol>failure</responseSymbol>
          <shouldHandoff>false</shouldHandoff>
          <transitionValue>0.0</transitionValue>
          <destination>
            <refId>65281656-4a99-4ace-a063-20addf7b4090</refId>
          </destination>
          <source>
            <refId>8cf69600-4e13-460e-95cf-c34bf76535eb</refId>
          </source>
          <positions>
            <point>
              <x>590.0</x>
              <y>83.0</y>
            </point>
            <point>
              <x>379.0</x>
              <y>259.0</y>
            </point>
          </positions>
          <labelPosition>
            <x>333.0</x>
            <y>0.0</y>
          </labelPosition>
        </transition>
      </transitions>
      <properties/>
      <opRef>
        <refId>b7d3217b-b3df-4a9e-8219-b52430fa1703</refId>
      </opRef>
      <assignments/>
      <throttleSize>0</throttleSize>
    </step>
    <step id="70e411e8-3910-463c-bb73-77100f7c78a0">
      <annotation></annotation>
      <name>Poll LCE</name>
      <bounds>
        <x>545.0</x>
        <y>390.0</y>
      </bounds>
      <layer>-1</layer>
      <hideInbound>false</hideInbound>
      <addResultToRunContext>false</addResultToRunContext>
      <isCriticalStep>false</isCriticalStep>
      <isNonBlocking>false</isNonBlocking>
      <isParallelStep>false</isParallelStep>
      <isSingleResponse>false</isSingleResponse>
      <recordInHistory>false</recordInHistory>
      <recordRawOutput>false</recordRawOutput>
      <recordPrimaryOutput>false</recordPrimaryOutput>
      <checkPointStep>true</checkPointStep>
      <historyCheckPointStep>true</historyCheckPointStep>
      <scriptResultStep>false</scriptResultStep>
      <userPrompt></userPrompt>
      <bindings>
        <userInputBinding id="121c7199-5695-42fd-bf2e-70538136713b">
          <annotation></annotation>
          <assignFromContext>true</assignFromContext>
          <assignToContext>true</assignToContext>
          <inputType>STRING</inputType>
          <isList>false</isList>
          <required>false</required>
          <isPersisted>true</isPersisted>
          <inputSymbol>serviceInstanceId</inputSymbol>
          <listDelimiter>,</listDelimiter>
          <record>false</record>
          <prompt></prompt>
          <isMultiSelect>false</isMultiSelect>
          <sourceDelimiter>|</sourceDelimiter>
        </userInputBinding>
        <userInputBinding id="f031a6b1-e687-43b5-88f2-1c9fbfa66dec">
          <annotation></annotation>
          <assignFromContext>true</assignFromContext>
          <assignToContext>true</assignToContext>
          <inputType>STRING</inputType>
          <isList>false</isList>
          <required>false</required>
          <isPersisted>true</isPersisted>
          <inputSymbol>userIdentifier</inputSymbol>
          <listDelimiter>,</listDelimiter>
          <record>false</record>
          <prompt></prompt>
          <isMultiSelect>false</isMultiSelect>
          <sourceDelimiter>|</sourceDelimiter>
        </userInputBinding>
      </bindings>
      <transitions>
        <transition id="aaa875da-b185-4131-861a-7ec299f3109f">
          <annotation></annotation>
          <name>success</name>
          <command>NEXT</command>
          <linkMode>false</linkMode>
          <responseSymbol>success</responseSymbol>
          <shouldHandoff>false</shouldHandoff>
          <transitionValue>0.0</transitionValue>
          <destination>
            <refId>41aa03e5-f92a-458e-86c1-78b326a6817d</refId>
          </destination>
          <source>
            <refId>70e411e8-3910-463c-bb73-77100f7c78a0</refId>
          </source>
          <positions>
            <point>
              <x>673.0</x>
              <y>382.0</y>
            </point>
            <point>
              <x>393.0</x>
              <y>474.0</y>
            </point>
          </positions>
          <labelPosition>
            <x>333.0</x>
            <y>0.0</y>
          </labelPosition>
        </transition>
        <transition id="0614ba20-ddcc-4503-bf0d-f2ced3f8cd6f">
          <annotation></annotation>
          <name>failure</name>
          <command>NEXT</command>
          <linkMode>false</linkMode>
          <responseSymbol>failure</responseSymbol>
          <shouldHandoff>false</shouldHandoff>
          <transitionValue>0.0</transitionValue>
          <destination>
            <refId>65281656-4a99-4ace-a063-20addf7b4090</refId>
          </destination>
          <source>
            <refId>70e411e8-3910-463c-bb73-77100f7c78a0</refId>
          </source>
          <positions>
            <point>
              <x>944.0</x>
              <y>378.0</y>
            </point>
            <point>
              <x>650.0</x>
              <y>255.0</y>
            </point>
          </positions>
          <labelPosition>
            <x>333.0</x>
            <y>0.0</y>
          </labelPosition>
        </transition>
      </transitions>
      <properties/>
      <opRef>
        <refId>b9559f3e-6996-431b-89bf-fac024e4cd15</refId>
      </opRef>
      <assignments/>
      <throttleSize>0</throttleSize>
    </step>
    <step id="2b32adc4-486d-49c0-a56f-507bccff5c68">
      <annotation></annotation>
      <name>Execute LCE</name>
      <bounds>
        <x>702.0</x>
        <y>330.0</y>
      </bounds>
      <layer>-1</layer>
      <hideInbound>false</hideInbound>
      <addResultToRunContext>false</addResultToRunContext>
      <isCriticalStep>false</isCriticalStep>
      <isNonBlocking>false</isNonBlocking>
      <isParallelStep>false</isParallelStep>
      <isSingleResponse>false</isSingleResponse>
      <recordInHistory>false</recordInHistory>
      <recordRawOutput>false</recordRawOutput>
      <recordPrimaryOutput>false</recordPrimaryOutput>
      <checkPointStep>true</checkPointStep>
      <historyCheckPointStep>true</historyCheckPointStep>
      <scriptResultStep>false</scriptResultStep>
      <userPrompt></userPrompt>
      <bindings>
        <userInputBinding id="608f537c-7bdb-4109-8237-bf44eac8772a">
          <annotation></annotation>
          <assignFromContext>true</assignFromContext>
          <assignToContext>true</assignToContext>
          <inputType>STRING</inputType>
          <isList>false</isList>
          <required>false</required>
          <isPersisted>true</isPersisted>
          <inputSymbol>userIdentifier</inputSymbol>
          <listDelimiter>,</listDelimiter>
          <record>false</record>
          <prompt></prompt>
          <isMultiSelect>false</isMultiSelect>
          <sourceDelimiter>|</sourceDelimiter>
        </userInputBinding>
        <userInputBinding id="22ac4175-4316-4f1f-8bc5-58563c1c2e13">
          <annotation></annotation>
          <fromContextKey>serverGrpId</fromContextKey>
          <assignFromContext>true</assignFromContext>
          <assignToContext>true</assignToContext>
          <inputType>STRING</inputType>
          <isList>false</isList>
          <required>true</required>
          <isPersisted>true</isPersisted>
          <inputSymbol>componentId</inputSymbol>
          <listDelimiter>,</listDelimiter>
          <record>false</record>
          <prompt>32fb6761-dd35-44f8-a349-6c391d2650b4.22ac4175-4316-4f1f-8bc5-58563c1c2e13.prompt</prompt>
          <isMultiSelect>false</isMultiSelect>
          <sourceDelimiter>|</sourceDelimiter>
        </userInputBinding>
        <userInputBinding id="3a009096-ad7f-4830-a3ed-d732490b51e3">
          <annotation></annotation>
          <assignFromContext>true</assignFromContext>
          <assignToContext>true</assignToContext>
          <inputType>STRING</inputType>
          <isList>false</isList>
          <required>true</required>
          <isPersisted>true</isPersisted>
          <inputSymbol>serviceInstanceId</inputSymbol>
          <listDelimiter>,</listDelimiter>
          <record>false</record>
          <prompt>32fb6761-dd35-44f8-a349-6c391d2650b4.3a009096-ad7f-4830-a3ed-d732490b51e3.prompt</prompt>
          <isMultiSelect>false</isMultiSelect>
          <sourceDelimiter>|</sourceDelimiter>
        </userInputBinding>
      </bindings>
      <transitions>
        <transition id="b205223c-3f5f-4297-b309-324205e71939">
          <annotation></annotation>
          <name>failure</name>
          <command>NEXT</command>
          <linkMode>false</linkMode>
          <responseSymbol>failure</responseSymbol>
          <shouldHandoff>false</shouldHandoff>
          <transitionValue>0.0</transitionValue>
          <destination>
            <refId>65281656-4a99-4ace-a063-20addf7b4090</refId>
          </destination>
          <source>
            <refId>2b32adc4-486d-49c0-a56f-507bccff5c68</refId>
          </source>
          <positions>
            <point>
              <x>932.0</x>
              <y>282.0</y>
            </point>
            <point>
              <x>650.0</x>
              <y>255.0</y>
            </point>
          </positions>
          <labelPosition>
            <x>333.0</x>
            <y>0.0</y>
          </labelPosition>
        </transition>
        <transition id="25f641d0-9030-4794-82c5-53d1fd20e3bb">
          <annotation></annotation>
          <name>success</name>
          <command>NEXT</command>
          <linkMode>false</linkMode>
          <responseSymbol>success</responseSymbol>
          <shouldHandoff>false</shouldHandoff>
          <transitionValue>0.0</transitionValue>
          <destination>
            <refId>70e411e8-3910-463c-bb73-77100f7c78a0</refId>
          </destination>
          <source>
            <refId>2b32adc4-486d-49c0-a56f-507bccff5c68</refId>
          </source>
          <positions>
            <point>
              <x>1209.0</x>
              <y>316.0</y>
            </point>
            <point>
              <x>1221.0</x>
              <y>412.0</y>
            </point>
          </positions>
          <labelPosition>
            <x>333.0</x>
            <y>0.0</y>
          </labelPosition>
        </transition>
      </transitions>
      <properties/>
      <opRef>
        <refId>21a176ba-d59f-4dfe-9b15-a593a2946716</refId>
      </opRef>
      <assignments/>
      <throttleSize>0</throttleSize>
    </step>
    <step id="2bea90ee-08a2-4090-9fa5-5ef5af95b4d9">
      <annotation>32fb6761-dd35-44f8-a349-6c391d2650b4.2bea90ee-08a2-4090-9fa5-5ef5af95b4d9.description</annotation>
      <name>Add Pattern</name>
      <bounds>
        <x>243.0</x>
        <y>0.0</y>
      </bounds>
      <layer>-1</layer>
      <hideInbound>false</hideInbound>
      <iconSpec id="b1994bc7-a022-4643-b649-b0ef994c52c8">
        <baseIcon>calculator.png</baseIcon>
        <basePath>Others</basePath>
        <readOnly>false</readOnly>
        <layers/>
      </iconSpec>
      <addResultToRunContext>false</addResultToRunContext>
      <isCriticalStep>false</isCriticalStep>
      <isNonBlocking>false</isNonBlocking>
      <isParallelStep>false</isParallelStep>
      <isSingleResponse>false</isSingleResponse>
      <recordInHistory>false</recordInHistory>
      <recordRawOutput>true</recordRawOutput>
      <recordPrimaryOutput>true</recordPrimaryOutput>
      <checkPointStep>true</checkPointStep>
      <historyCheckPointStep>true</historyCheckPointStep>
      <scriptResultStep>false</scriptResultStep>
      <userPrompt></userPrompt>
      <bindings>
        <userInputBinding id="0e0585fe-309d-4da3-a928-85e17a4d1758">
          <annotation></annotation>
          <fromContextKey>patternCount</fromContextKey>
          <assignFromContext>true</assignFromContext>
          <assignToContext>true</assignToContext>
          <inputType>STRING</inputType>
          <isList>false</isList>
          <required>true</required>
          <isPersisted>true</isPersisted>
          <inputSymbol>value1</inputSymbol>
          <listDelimiter>,</listDelimiter>
          <record>false</record>
          <validationFormat>
            <refId>69c5e11d-2f62-488c-b02b-9c507dcb9088</refId>
            <refName>numeric</refName>
          </validationFormat>
          <prompt>32fb6761-dd35-44f8-a349-6c391d2650b4.0e0585fe-309d-4da3-a928-85e17a4d1758.prompt</prompt>
          <isMultiSelect>false</isMultiSelect>
          <sourceDelimiter>|</sourceDelimiter>
        </userInputBinding>
        <userInputBinding id="e8f3c8a8-0bcc-4209-b0e7-31fc60462237">
          <annotation></annotation>
          <fromContextKey>addServers</fromContextKey>
          <assignFromContext>true</assignFromContext>
          <assignToContext>true</assignToContext>
          <inputType>STRING</inputType>
          <isList>false</isList>
          <required>true</required>
          <isPersisted>true</isPersisted>
          <inputSymbol>value2</inputSymbol>
          <listDelimiter>,</listDelimiter>
          <record>false</record>
          <validationFormat>
            <refId>69c5e11d-2f62-488c-b02b-9c507dcb9088</refId>
            <refName>numeric</refName>
          </validationFormat>
          <prompt></prompt>
          <isMultiSelect>false</isMultiSelect>
          <sourceDelimiter>|</sourceDelimiter>
        </userInputBinding>
        <staticBinding id="94975a4a-a8bb-46b3-9c15-30e6eda9c9bd">
          <annotation></annotation>
          <toContextKey></toContextKey>
          <fromContextKey></fromContextKey>
          <assignFromContext>false</assignFromContext>
          <assignToContext>false</assignToContext>
          <inputType>STRING</inputType>
          <recordKey></recordKey>
          <isList>false</isList>
          <required>false</required>
          <isPersisted>true</isPersisted>
          <inputSymbol>operation</inputSymbol>
          <listDelimiter></listDelimiter>
          <value>+</value>
          <record>false</record>
        </staticBinding>
      </bindings>
      <transitions>
        <transition id="85cfb4fa-d188-46a8-924e-b590edfc392e">
          <annotation></annotation>
          <name>failure</name>
          <command>NEXT</command>
          <linkMode>false</linkMode>
          <responseSymbol>failure</responseSymbol>
          <shouldHandoff>false</shouldHandoff>
          <transitionValue>0.0</transitionValue>
          <destination>
            <refId>65281656-4a99-4ace-a063-20addf7b4090</refId>
          </destination>
          <source>
            <refId>2bea90ee-08a2-4090-9fa5-5ef5af95b4d9</refId>
          </source>
          <positions>
            <point>
              <x>293.0</x>
              <y>25.0</y>
            </point>
            <point>
              <x>379.0</x>
              <y>259.0</y>
            </point>
          </positions>
          <labelPosition>
            <x>333.0</x>
            <y>0.0</y>
          </labelPosition>
        </transition>
        <transition id="057091f0-9063-4ffa-acc6-8831e330366e">
          <annotation></annotation>
          <name>success</name>
          <command>NEXT</command>
          <linkMode>false</linkMode>
          <responseSymbol>success</responseSymbol>
          <shouldHandoff>false</shouldHandoff>
          <transitionValue>0.0</transitionValue>
          <destination>
            <refId>58caf5a2-011e-4ff8-9af8-e5587d74456e</refId>
          </destination>
          <source>
            <refId>2bea90ee-08a2-4090-9fa5-5ef5af95b4d9</refId>
          </source>
          <positions>
            <point>
              <x>293.0</x>
              <y>25.0</y>
            </point>
            <point>
              <x>437.0</x>
              <y>19.0</y>
            </point>
          </positions>
          <labelPosition>
            <x>333.0</x>
            <y>0.0</y>
          </labelPosition>
        </transition>
      </transitions>
      <properties/>
      <opRef>
        <refId>37fbd782-48f2-4f66-b1b9-7f32c2b707bd</refId>
      </opRef>
      <assignments>
        <flowVariableAssignment id="2345f79b-2db7-4e67-9fee-825da1b25ada">
          <annotation></annotation>
          <name>assignment</name>
          <action>OVERWRITE</action>
          <assignmentTargetType>FLOW_VARIABLE</assignmentTargetType>
          <contextKey>patternCount</contextKey>
          <expression id="c9c5cb78-bf9e-4344-b59f-5e002149ae86">
            <annotation></annotation>
            <name>Result Field: result</name>
            <fieldName>result</fieldName>
            <sourceType>RAWRESULT</sourceType>
            <filters/>
          </expression>
        </flowVariableAssignment>
      </assignments>
      <throttleSize>0</throttleSize>
    </step>
    <step id="85eeedc0-a8c8-4179-898c-46f6613ac26c">
      <annotation></annotation>
      <name>Add Process Instance</name>
      <bounds>
        <x>551.0</x>
        <y>0.0</y>
      </bounds>
      <layer>-1</layer>
      <hideInbound>false</hideInbound>
      <addResultToRunContext>false</addResultToRunContext>
      <isCriticalStep>false</isCriticalStep>
      <isNonBlocking>false</isNonBlocking>
      <isParallelStep>false</isParallelStep>
      <isSingleResponse>false</isSingleResponse>
      <recordInHistory>false</recordInHistory>
      <recordRawOutput>false</recordRawOutput>
      <recordPrimaryOutput>false</recordPrimaryOutput>
      <checkPointStep>true</checkPointStep>
      <historyCheckPointStep>true</historyCheckPointStep>
      <scriptResultStep>false</scriptResultStep>
      <userPrompt></userPrompt>
      <bindings>
        <userInputBinding id="5b8180f0-1c13-4559-b6e6-d4ef213c2f62">
          <annotation></annotation>
          <assignFromContext>true</assignFromContext>
          <assignToContext>true</assignToContext>
          <inputType>STRING</inputType>
          <isList>false</isList>
          <required>true</required>
          <isPersisted>true</isPersisted>
          <inputSymbol>userIdentifier</inputSymbol>
          <listDelimiter>,</listDelimiter>
          <record>false</record>
          <prompt></prompt>
          <isMultiSelect>false</isMultiSelect>
          <sourceDelimiter>|</sourceDelimiter>
        </userInputBinding>
        <staticBinding id="8ff2614c-fa5c-4d9e-9140-75c71f5e20c8">
          <annotation></annotation>
          <assignFromContext>true</assignFromContext>
          <assignToContext>true</assignToContext>
          <inputType>STRING</inputType>
          <isList>false</isList>
          <required>true</required>
          <isPersisted>true</isPersisted>
          <inputSymbol>propertyName</inputSymbol>
          <listDelimiter>,</listDelimiter>
          <value>count</value>
          <record>false</record>
        </staticBinding>
        <userInputBinding id="7a81fa68-e3fe-4456-83b0-41122c13bc61">
          <annotation></annotation>
          <fromContextKey>serverGrpId</fromContextKey>
          <assignFromContext>true</assignFromContext>
          <assignToContext>true</assignToContext>
          <inputType>STRING</inputType>
          <isList>false</isList>
          <required>true</required>
          <isPersisted>true</isPersisted>
          <inputSymbol>componentId</inputSymbol>
          <listDelimiter>,</listDelimiter>
          <record>false</record>
          <prompt>32fb6761-dd35-44f8-a349-6c391d2650b4.7a81fa68-e3fe-4456-83b0-41122c13bc61.prompt</prompt>
          <isMultiSelect>false</isMultiSelect>
          <sourceDelimiter>|</sourceDelimiter>
        </userInputBinding>
      </bindings>
      <transitions>
        <transition id="ef0a5647-e1e1-4da1-b569-deefabd4b0af">
          <annotation></annotation>
          <name>success</name>
          <command>NEXT</command>
          <linkMode>false</linkMode>
          <responseSymbol>success</responseSymbol>
          <shouldHandoff>false</shouldHandoff>
          <transitionValue>0.0</transitionValue>
          <destination>
            <refId>33515130-d3a5-4d79-b8b9-f4f320029371</refId>
          </destination>
          <source>
            <refId>85eeedc0-a8c8-4179-898c-46f6613ac26c</refId>
          </source>
          <positions>
            <point>
              <x>424.0</x>
              <y>73.0</y>
            </point>
            <point>
              <x>742.0</x>
              <y>156.0</y>
            </point>
          </positions>
          <labelPosition>
            <x>333.0</x>
            <y>0.0</y>
          </labelPosition>
        </transition>
        <transition id="48ba0193-d0aa-4ca5-b3a4-56c54e79c9ee">
          <annotation></annotation>
          <name>failure</name>
          <command>NEXT</command>
          <linkMode>false</linkMode>
          <responseSymbol>failure</responseSymbol>
          <shouldHandoff>false</shouldHandoff>
          <transitionValue>0.0</transitionValue>
          <destination>
            <refId>65281656-4a99-4ace-a063-20addf7b4090</refId>
          </destination>
          <source>
            <refId>85eeedc0-a8c8-4179-898c-46f6613ac26c</refId>
          </source>
          <positions>
            <point>
              <x>695.0</x>
              <y>69.0</y>
            </point>
            <point>
              <x>650.0</x>
              <y>255.0</y>
            </point>
          </positions>
          <labelPosition>
            <x>333.0</x>
            <y>0.0</y>
          </labelPosition>
        </transition>
      </transitions>
      <properties/>
      <opRef>
        <refId>0da02fc5-e200-47d8-8d26-f490f1678834</refId>
      </opRef>
      <assignments>
        <flowVariableAssignment id="cc8b1bc8-2c66-4385-aa0d-1f1790ffb1d3">
          <annotation></annotation>
          <name>assignment</name>
          <action>OVERWRITE</action>
          <assignmentTargetType>FLOW_VARIABLE</assignmentTargetType>
          <contextKey>processInstanceId</contextKey>
          <expression id="330c5fac-1c41-4ef5-a781-ee6f90456972">
            <annotation></annotation>
            <name>Result Field: processInstanceId</name>
            <fieldName>processInstanceId</fieldName>
            <sourceType>RAWRESULT</sourceType>
            <filters/>
          </expression>
        </flowVariableAssignment>
      </assignments>
      <throttleSize>0</throttleSize>
    </step>
    <returnStep id="65281656-4a99-4ace-a063-20addf7b4090">
      <annotation></annotation>
      <name>Error : failure</name>
      <bounds>
        <x>329.0</x>
        <y>225.0</y>
      </bounds>
      <layer>-1</layer>
      <hideInbound>false</hideInbound>
      <addResultToRunContext>false</addResultToRunContext>
      <isCriticalStep>false</isCriticalStep>
      <isNonBlocking>false</isNonBlocking>
      <isParallelStep>false</isParallelStep>
      <isSingleResponse>false</isSingleResponse>
      <recordInHistory>false</recordInHistory>
      <recordRawOutput>true</recordRawOutput>
      <recordPrimaryOutput>true</recordPrimaryOutput>
      <checkPointStep>true</checkPointStep>
      <historyCheckPointStep>true</historyCheckPointStep>
      <scriptResultStep>false</scriptResultStep>
      <userPrompt></userPrompt>
      <bindings>
        <staticBinding id="9bfe6650-99ff-403b-a663-cfe7d7b04096">
          <annotation></annotation>
          <assignFromContext>false</assignFromContext>
          <assignToContext>false</assignToContext>
          <inputType>STRING</inputType>
          <isList>false</isList>
          <required>false</required>
          <isPersisted>true</isPersisted>
          <inputSymbol>processStatus</inputSymbol>
          <listDelimiter>,</listDelimiter>
          <value>Failed to add server to the server group</value>
          <record>false</record>
        </staticBinding>
      </bindings>
      <transitions>
        <transition id="cfdcf4bc-9feb-4b06-891b-acb412a3dba0">
          <annotation></annotation>
          <name>return</name>
          <command>NEXT</command>
          <linkMode>false</linkMode>
          <responseSymbol>failure</responseSymbol>
          <shouldHandoff>false</shouldHandoff>
          <transitionValue>0.0</transitionValue>
          <destination>
            <refId>65281656-4a99-4ace-a063-20addf7b4090</refId>
          </destination>
          <source>
            <refId>65281656-4a99-4ace-a063-20addf7b4090</refId>
          </source>
          <positions/>
        </transition>
      </transitions>
      <properties/>
      <returnStepType>ERROR</returnStepType>
      <assignments>
        <flowVariableAssignment id="9122f1e7-f443-4d88-a4f5-e56996320fac">
          <annotation></annotation>
          <name>assignment</name>
          <action>OVERWRITE</action>
          <assignmentTargetType>FLOW_OUTPUT_FIELD</assignmentTargetType>
          <contextKey>processStatus</contextKey>
          <expression id="ebbc3b51-d8f9-4d64-bf1e-0ededff6b62a">
            <annotation></annotation>
            <name>Input: processStatus</name>
            <fieldName>processStatus</fieldName>
            <sourceType>INPUT</sourceType>
            <filters/>
          </expression>
        </flowVariableAssignment>
      </assignments>
    </returnStep>
    <returnStep id="41aa03e5-f92a-458e-86c1-78b326a6817d">
      <annotation></annotation>
      <name>Resolved : success</name>
      <bounds>
        <x>312.0</x>
        <y>390.0</y>
      </bounds>
      <layer>-1</layer>
      <hideInbound>false</hideInbound>
      <addResultToRunContext>false</addResultToRunContext>
      <isCriticalStep>false</isCriticalStep>
      <isNonBlocking>false</isNonBlocking>
      <isParallelStep>false</isParallelStep>
      <isSingleResponse>false</isSingleResponse>
      <recordInHistory>false</recordInHistory>
      <recordRawOutput>true</recordRawOutput>
      <recordPrimaryOutput>true</recordPrimaryOutput>
      <checkPointStep>true</checkPointStep>
      <historyCheckPointStep>true</historyCheckPointStep>
      <scriptResultStep>false</scriptResultStep>
      <userPrompt></userPrompt>
      <bindings/>
      <transitions>
        <transition id="6d3d41fc-3cc3-4df2-8111-d0524c007f14">
          <annotation></annotation>
          <name>return</name>
          <command>NEXT</command>
          <linkMode>false</linkMode>
          <responseSymbol>success</responseSymbol>
          <shouldHandoff>false</shouldHandoff>
          <transitionValue>0.0</transitionValue>
          <destination>
            <refId>41aa03e5-f92a-458e-86c1-78b326a6817d</refId>
          </destination>
          <source>
            <refId>41aa03e5-f92a-458e-86c1-78b326a6817d</refId>
          </source>
          <positions/>
        </transition>
      </transitions>
      <properties/>
      <returnStepType>RESOLVED</returnStepType>
      <assignments/>
    </returnStep>
  </steps>
  <startSteps>0633dafc-b74b-40ec-aae8-f13969965b24</startSteps>
</flow>